Metadata-Version: 2.1
Name: mhcbooster
Version: 2.2.0
Home-page: https://github.com/caronlab/mhcbooster
Author: Ruimin Wang
Author-email: ruimin.wang@yale.edu
License: GPL-3.0
Classifier: Programming Language :: Python :: 3.10
Classifier: License :: OSI Approved :: GNU General Public License v3 (GPLv3)
Classifier: Operating System :: OS Independent
Requires-Python: ==3.10
License-File: LICENSE
Requires-Dist: mhcflurry ==2.1.4
Requires-Dist: tensorflow ==2.16.1
Requires-Dist: tensorflow-probability ==0.24.0
Requires-Dist: numpy
Requires-Dist: pandas ==2.2.3
Requires-Dist: mhcnames ==0.4.8
Requires-Dist: pyteomics
Requires-Dist: lxml
Requires-Dist: matplotlib
Requires-Dist: scipy
Requires-Dist: scikit-learn ==1.5.2
Requires-Dist: deeplc
Requires-Dist: xmltodict
Requires-Dist: hyperopt
Requires-Dist: tqdm
Requires-Dist: protobuf ==4.25.5
Requires-Dist: matplotlib-venn
Requires-Dist: peptdeep ==1.3.0
Requires-Dist: pydivsufsort
Requires-Dist: mokapot ==0.10.0
Requires-Dist: im2deep
Requires-Dist: PySide6
Requires-Dist: statsmodels ==0.14.4
Requires-Dist: koinapy ==0.0.9
Requires-Dist: adjustText
